LICENSE
ascii_art/__init__.py
ascii_art/__main__.py
cli_art-0.0.1.dist-info/LICENSE
cli_art-0.0.1.dist-info/METADATA
cli_art-0.0.1.dist-info/WHEEL
cli_art-0.0.1.dist-info/entry_points.txt
cli_art-0.0.1.dist-info/RECORD
