Metadata-Version: 2.1
Name: cli-art
Version: 0.0.1
Summary: ASCII art generator with multiple customization parameters
Home-page: https://github.com/dawsonbooth/ascii-art
License: MIT
Keywords: cli,console,ascii,art,font,image
Author: Dawson Booth
Author-email: pypi@dawsonbooth.com
Requires-Python: >=3.8,<4.0
Classifier: Environment :: Console
Classifier: License :: OSI Approved :: MIT License
Classifier: Operating System :: OS Independent
Classifier: Programming Language :: Python :: 3
Classifier: Programming Language :: Python :: 3.8
Classifier: Programming Language :: Python :: 3.9
Classifier: Programming Language :: Python :: 3.10
Classifier: Programming Language :: Python :: 3.11
Classifier: Programming Language :: Python :: 3.12
Requires-Dist: Pillow (>=9.2.0,<10.0.0)
Project-URL: Documentation, https://dawsonbooth.github.io/ascii-art
Project-URL: Repository, https://github.com/dawsonbooth/ascii-art
